aparecium/__init__.py
aparecium/__main__.py
aparecium/api.py
aparecium/config.py
aparecium/version.py
aparecium/data/datasets.py
aparecium/data/plans.py
aparecium/decoding/__init__.py
aparecium/decoding/embedding_scorer.py
aparecium/eval/eval_suite.py
aparecium/eval/metrics.py
aparecium/infer/decode.py
aparecium/infer/service.py
aparecium/models/constraints.py
aparecium/models/decoder.py
aparecium/models/emb_adapter.py
aparecium/models/sketcher.py
aparecium/models/surrogate_r.py
aparecium/scripts/build_faiss.py
aparecium/scripts/embed_mpnet.py
aparecium/scripts/extract_from_db.py
aparecium/scripts/inspect_posts.py
aparecium/scripts/invert_once.py
aparecium/scripts/prep_shards.py
aparecium/scripts/preview_invert.py
aparecium/scripts/split_jsonl.py
aparecium/train/train_s1_supervised.py
aparecium/train/train_s2_scst.py
aparecium/train/train_surrogate_r.py
aparecium/utils/common.py
aparecium/utils/tokens.py
aparecium-1.0.0.dist-info/licenses/LICENSE
aparecium-1.0.0.dist-info/METADATA
aparecium-1.0.0.dist-info/WHEEL
aparecium-1.0.0.dist-info/top_level.txt
aparecium-1.0.0.dist-info/RECORD
