Metadata-Version: 2.4
Name: aparecium
Version: 1.0.0
Summary: Aparecium v2: pooled MPNet embedding reversal for crypto social-media posts.
Author: SentiChain
Project-URL: Homepage, https://github.com/SentiChain/aparecium
Project-URL: Source Code, https://github.com/SentiChain/aparecium
Project-URL: Tracker, https://github.com/SentiChain/aparecium/issues
Requires-Python: >=3.9
License-File: LICENSE
Requires-Dist: torch>=2.0
Requires-Dist: transformers>=4.40
Requires-Dist: tqdm
Requires-Dist: sentence-transformers>=2.2
Requires-Dist: huggingface-hub>=0.25
Requires-Dist: numpy>=1.23
Requires-Dist: fastapi>=0.110
Requires-Dist: uvicorn>=0.23
Provides-Extra: dev
Dynamic: license-file
